setup.cfg
setup.py
src/imongo/__init__.py
src/imongo/helps.py
src/imongo/imongo.py
src/imongo/util.py
src/ipython_mongo.egg-info/PKG-INFO
src/ipython_mongo.egg-info/SOURCES.txt
src/ipython_mongo.egg-info/dependency_links.txt
src/ipython_mongo.egg-info/not-zip-safe
src/ipython_mongo.egg-info/requires.txt
src/ipython_mongo.egg-info/top_level.txt