Metadata-Version: 1.1
Name: ipython-mongo
Version: 0.3.2
Summary: MONGODB access via IPython
Home-page: https://github.com/Bloodevil/ipython_mongo
Author: Yeaji Shin
Author-email: yeahjishin@gmail.com
License: MIT
Download-URL: https://github.com/Bloodevil/ipython_mongo/tarball/0.2
Keywords: database,ipython,mongodb,shell,imongo
Platform: UNKNOWN
Classifier: Environment :: Console
Classifier: License :: OSI Approved :: MIT License
Classifier: Framework :: IPython
Classifier: Topic :: Database
Classifier: Topic :: Database :: Front-Ends
Classifier: Programming Language :: Python :: 2
